project/__init__.py
project/__main__.py
project/api.py
project/config.py
project/constants.py
project/db.py
project/models.py
project/paperdao.py
project/routes.py
project/swagger.yml
project/util.py
project/views.py
project/static/http_servers.json
project/static/qresp_servers.json
project/static/robots.txt
project/static/v1_0.json
project/static/v1_1.json
project/static/css/css-plugin-collections.css
project/static/css/custom/custom.css
project/static/css/datatables/jquery.dataTables.css
project/static/css/datatables/jquery.dataTables.min.css
project/static/css/fonts/.DS_Store_1
project/static/css/fonts/Pe-icon-7-strokebb1d.eot
project/static/css/fonts/Pe-icon-7-strokebb1d.svg
project/static/css/fonts/Pe-icon-7-strokebb1d.ttf
project/static/css/fonts/Pe-icon-7-strokebb1d.woff
project/static/css/fonts/Pe-icon-7-strokebb1d_1.eot
project/static/css/fonts/Pe-icon-7-strokebb1d_1.svg
project/static/css/fonts/Pe-icon-7-strokebb1d_1.ttf
project/static/css/fonts/Pe-icon-7-strokebb1d_1.woff
project/static/css/fonts/Pe-icon-7-stroked41d.eot
project/static/css/fonts/Pe-icon-7-stroked41d_1.eot
project/static/css/fonts/fontawesome-webfont3295.eot
project/static/css/fonts/fontawesome-webfont3295.svg
project/static/css/fonts/fontawesome-webfont3295.ttf
project/static/css/fonts/fontawesome-webfont3295.woff
project/static/css/fonts/fontawesome-webfont3295.woff2
project/static/css/fonts/fontawesome-webfont3295_1.eot
project/static/css/fonts/fontawesome-webfont3295_1.svg
project/static/css/fonts/fontawesome-webfont3295_1.ttf
project/static/css/fonts/fontawesome-webfont3295_1.woff
project/static/css/fonts/fontawesome-webfont3295_1.woff2
project/static/css/fonts/fontawesome-webfontd41d.eot
project/static/css/fonts/fontawesome-webfontd41d_1.eot
project/static/css/fonts/glyphicons-halflings-regular.ttf
project/static/css/fonts/glyphicons-halflings-regular.woff
project/static/css/fonts/glyphicons-halflings-regular.woff2
project/static/css/fonts/glyphicons-halflings-regular_1.ttf
qresp-1.2.1.dist-info/METADATA
qresp-1.2.1.dist-info/WHEEL
qresp-1.2.1.dist-info/entry_points.txt
qresp-1.2.1.dist-info/top_level.txt
qresp-1.2.1.dist-info/RECORD
